lrc_core/__init__.py
lrc_core/__main__.py
lrc_core/config.py
lrc_core/exception.py
lrc_core/recorder_adapters/__init__.py
lrc_core/recorder_adapters/epiphan_base.py
lrc_core/recorder_adapters/extron_smp.py
lrc_core/tests/test_epiphan.py
lrc_core/tests/test_extron_smp.py
lrc_core-0.3.1.dist-info/METADATA
lrc_core-0.3.1.dist-info/WHEEL
lrc_core-0.3.1.dist-info/RECORD
